ckip2tei/__init__.py
ckip2tei/ckip/__init__.py
ckip2tei/ckip/model/__init__.py
ckip2tei/ckip/model/ckip.py
ckip2tei/ckip/segmenter.py
ckip2tei/ckip/transformer/__init__.py
ckip2tei/ckip/transformer/transformer.py
ckip2tei/config/__init__.py
ckip2tei/config/environment.py
ckip2tei/tei/__init__.py
ckip2tei/tei/tags/body/__init__.py
ckip2tei/tei/tags/body/body.py
ckip2tei/tei/tags/body/taggers/__init__.py
ckip2tei/tei/tags/body/taggers/base.py
ckip2tei/tei/tags/body/taggers/cleaners/__init__.py
ckip2tei/tei/tags/body/taggers/cleaners/base.py
ckip2tei/tei/tags/body/taggers/cleaners/cleaners.py
ckip2tei/tei/tags/body/taggers/taggers.py
ckip2tei/tei/tags/head/__init__.py
ckip2tei/tei/tags/head/head.py
ckip2tei/tei/tei.py
ckip2tei/tei/utils/__init__.py
ckip2tei/tei/utils/body.py
ckip2tei/tei/utils/date.py
ckip2tei-1.1.3.dist-info/LICENSE
ckip2tei-1.1.3.dist-info/METADATA
ckip2tei-1.1.3.dist-info/WHEEL
ckip2tei-1.1.3.dist-info/RECORD
