Metadata-Version: 2.1
Name: ckip2tei
Version: 1.1.3
Summary: A Python package that asynchronously segments JSON data into TEI XML format.
Author: Retr0327
Requires-Python: >=3.10,<4.0
Classifier: Programming Language :: Python :: 3
Classifier: Programming Language :: Python :: 3.10
Classifier: Programming Language :: Python :: 3.11
Classifier: Programming Language :: Python :: 3.12
Requires-Dist: ckip-transformers (>=0.3.4,<0.4.0)
Requires-Dist: pydantic (>=2.7.0,<3.0.0)
Requires-Dist: pydantic-settings (>=2.2.1,<3.0.0)
